[
    {
        "title": "D'Majestic Place by Swiss-Garden",
        "link": "https://www.google.com/maps/place/D%27Majestic+Place+by+Swiss-Garden/data=!4m10!3m9!1s0x31cc3626b2e5c1db:0xaf5b0fb6a37a007f!5m2!4m1!1i2!8m2!3d3.136627!4d101.711672!16s%2Fg%2F11b6hwk2vv!19sChIJ28HlsiY2zDERfwB6o7YPW68?authuser=0&hl=en&rclk=1",
        "id": 1
    },
    {
        "title": "The Suites @ Times Square",
        "link": "https://www.google.com/maps/place/The+Suites+@+Times+Square/data=!4m10!3m9!1s0x31cc3628934618d7:0x21dcfb6e402d868e!5m2!4m1!1i2!8m2!3d3.142648!4d101.710672!16s%2Fg%2F1hg48nxyh!19sChIJ1xhGkyg2zDERjoYtQG773CE?authuser=0&hl=en&rclk=1",
        "id": 1
    },
    {
        "title": "The Place @ Cyberjaya",
        "link": "https://www.google.com/maps/place/The+Place+@+Cyberjaya/data=!4m10!3m9!1s0x31cdb7954f59c111:0x6c063c04485e3ea4!5m2!4m1!1i2!8m2!3d2.9372015!4d101.6623624!16s%2Fg%2F11b8c4m8zb!19sChIJEcFZT5W3zTERpD5eSAQ8Bmw?authuser=0&hl=en&rclk=1",
        "id": 1
    },
    {
        "title": "D PLACE CAFE",
        "link": "https://www.google.com/maps/place/D+PLACE+CAFE/data=!4m7!3m6!1s0x31cdb72438459cff:0x8fa68a3abda2f153!8m2!3d2.9371265!4d101.6621411!16s%2Fg%2F11rfng2_sm!19sChIJ_5xFOCS3zTERU_GivTqKpo8?authuser=0&hl=en&rclk=1",
        "id": 1
    },
    {
        "title": "The Artsy Place",
        "link": "https://www.google.com/maps/place/The+Artsy+Place/data=!4m7!3m6!1s0x31cdb5d89e8f7103:0xf60cae538833fedd!8m2!3d2.9816623!4d101.6634816!16s%2Fg%2F11l1md1q3t!19sChIJA3GPnti1zTER3f4ziFOuDPY?authuser=0&hl=en&rclk=1",
        "id": 1
    },
    {
        "title": "T Place Kopitiam",
        "link": "https://www.google.com/maps/place/T+Place+Kopitiam/data=!4m7!3m6!1s0x31cdb1b715a4cfe1:0xf08b21556feb80c3!8m2!3d2.9467692!4d101.5431988!16s%2Fg%2F11s48hxdmj!19sChIJ4c-kFbexzTERw4Drb1Uhi_A?authuser=0&hl=en&rclk=1",
        "id": 1
    },
    {
        "title": "Klinik Pergigian Dental Place Cyberjaya",
        "link": "https://www.google.com/maps/place/Klinik+Pergigian+Dental+Place+Cyberjaya/data=!4m7!3m6!1s0x31cdb721dac6ad55:0x81caef5246dbb25d!8m2!3d2.9233233!4d101.6607139!16s%2Fg%2F11s2m_xpfv!19sChIJVa3G2iG3zTERXbLbRlLvyoE?authuser=0&hl=en&rclk=1",
        "id": 1
    },
    {
        "title": "African Food Palace Amala joint",
        "link": "https://www.google.com/maps/place/African+Food+Palace+Amala+joint/data=!4m7!3m6!1s0x31cdb6601dd6a107:0x26ea998b35ded844!8m2!3d2.9370558!4d101.6622415!16s%2Fg%2F11cjp7s8g5!19sChIJB6HWHWC2zTERRNjeNYuZ6iY?authuser=0&hl=en&rclk=1",
        "id": 1
    },
    {
        "title": "Restoran Patin Place",
        "link": "https://www.google.com/maps/place/Restoran+Patin+Place/data=!4m7!3m6!1s0x31cdb47e81c654cd:0xdc54cce97fc65a13!8m2!3d2.9922879!4d101.6213985!16s%2Fg%2F1hc8wpyr_!19sChIJzVTGgX60zTERE1rGf-nMVNw?authuser=0&hl=en&rclk=1",
        "id": 1
    },
    {
        "title": "Aroi Thai @ Main Place",
        "link": "https://www.google.com/maps/place/Aroi+Thai+@+Main+Place/data=!4m7!3m6!1s0x31cdb393b2ff1af7:0x4d0d5222598f3285!8m2!3d3.02601!4d101.5809349!16s%2Fg%2F11flv97fxp!19sChIJ9xr_spOzzTERhTKPWSJSDU0?authuser=0&hl=en&rclk=1",
        "id": 1
    },
    {
        "title": "Home place Yati",
        "link": "https://www.google.com/maps/place/Home+place+Yati/data=!4m7!3m6!1s0x31cdab4a81ea4b11:0x5f13a67a3b264f37!8m2!3d3.034354!4d101.411315!16s%2Fg%2F11bvv57cd_!19sChIJEUvqgUqrzTERN08mO3qmE18?authuser=0&hl=en&rclk=1",
        "id": 1
    },
    {
        "title": "A Place Called Home",
        "link": "https://www.google.com/maps/place/A+Place+Called+Home/data=!4m10!3m9!1s0x31cc4a822ec2dacf:0x24fb293df1f46b90!5m2!4m1!1i2!8m2!3d3.06741!4d101.7044688!16s%2Fg%2F11c37_zs_q!19sChIJz9rCLoJKzDERkGv08T0p-yQ?authuser=0&hl=en&rclk=1",
        "id": 1
    },
    {
        "title": "A-Park",
        "link": "https://www.google.com/maps/place/A-Park/data=!4m7!3m6!1s0x31cdb41a7ab1c96d:0xeac0972e9f3708f4!8m2!3d2.9644627!4d101.6317197!16s%2Fg%2F11b7p_mmvr!19sChIJbcmxehq0zTER9Ag3ny6XwOo?authuser=0&hl=en&rclk=1",
        "id": 1
    },
    {
        "title": "A-Saloon Main Place - Highly Recommended Best Salon in USJ",
        "link": "https://www.google.com/maps/place/A-Saloon+Main+Place+-+Highly+Recommended+Best+Salon+in+USJ/data=!4m7!3m6!1s0x31cdb32fdd85d731:0x948d3bef6220d070!8m2!3d3.0265771!4d101.5811881!16s%2Fg%2F11f__lqp1h!19sChIJMdeF3S-zzTERcNAgYu87jZQ?authuser=0&hl=en&rclk=1",
        "id": 1
    },
    {
        "title": "The Palace Place",
        "link": "https://www.google.com/maps/place/The+Palace+Place/data=!4m7!3m6!1s0x31cdb1e968742ebd:0x5daa9218a6cd3c8e!8m2!3d3.1385059!4d101.6869895!16s%2Fg%2F11lb1c5vbb!19sChIJvS50aOmxzTERjjzNphiSql0?authuser=0&hl=en&rclk=1",
        "id": 1
    },
    {
        "title": "A's place",
        "link": "https://www.google.com/maps/place/A%27s+place/data=!4m7!3m6!1s0x31cc4cf5d6ba54b1:0x30506bceb4c73ae2!8m2!3d3.071887!4d101.58764!16s%2Fg%2F11cn0k7pxp!19sChIJsVS61vVMzDER4jrHtM5rUDA?authuser=0&hl=en&rclk=1",
        "id": 1
    },
    {
        "title": "U-Thant Place",
        "link": "https://www.google.com/maps/place/U-Thant+Place/data=!4m7!3m6!1s0x31cc372c7fb1b495:0xbda120fc3e5d8155!8m2!3d3.1568074!4d101.7231712!16s%2Fg%2F11g__1s2nt!19sChIJlbSxfyw3zDERVYFdPvwgob0?authuser=0&hl=en&rclk=1",
        "id": 1
    },
    {
        "title": "The Eye Place Optometrist Kota Kemuning",
        "link": "https://www.google.com/maps/place/The+Eye+Place+Optometrist+Kota+Kemuning/data=!4m7!3m6!1s0x31cdb391935d4d4b:0xdb312271336e9f72!8m2!3d3.005064!4d101.5351756!16s%2Fg%2F11tfnxs3rj!19sChIJS01dk5GzzTERcp9uM3EiMds?authuser=0&hl=en&rclk=1",
        "id": 1
    },
    {
        "title": "Main Place Mall USJ",
        "link": "https://www.google.com/maps/place/Main+Place+Mall+USJ/data=!4m7!3m6!1s0x31cdb32fdd85d731:0x8d716a8b3eb18476!8m2!3d3.02632!4d101.5811466!16s%2Fg%2F11b6bpx463!19sChIJMdeF3S-zzTERdoSxPotqcY0?authuser=0&hl=en&rclk=1",
        "id": 1
    },
    {
        "title": "Molly Fantasy @ Main Place",
        "link": "https://www.google.com/maps/place/Molly+Fantasy+@+Main+Place/data=!4m7!3m6!1s0x31cdb330268cd121:0xcaa87a816e8eae72!8m2!3d3.0265299!4d101.581059!16s%2Fg%2F11bc8ch90_!19sChIJIdGMJjCzzTERcq6OboF6qMo?authuser=0&hl=en&rclk=1",
        "id": 1
    },
    {
        "title": "Nam Heong Chicken Rice, Main Place Mall",
        "link": "https://www.google.com/maps/place/Nam+Heong+Chicken+Rice,+Main+Place+Mall/data=!4m7!3m6!1s0x31cdb32d8f48598d:0x5a466a737f0a81ec!8m2!3d3.0269363!4d101.5815052!16s%2Fg%2F11tk372wxr!19sChIJjVlIjy2zzTER7IEKf3NqRlo?authuser=0&hl=en&rclk=1",
        "id": 1
    },
    {
        "title": "ThatNicePlace",
        "link": "https://www.google.com/maps/place/ThatNicePlace/data=!4m10!3m9!1s0x31cc1788b7fac18d:0xc3f10a6423d4f617!5m2!4m1!1i2!8m2!3d3.3555001!4d101.8215019!16s%2Fg%2F11h6r_c3dr!19sChIJjcH6t4gXzDERF_bUI2QK8cM?authuser=0&hl=en&rclk=1",
        "id": 1
    }
]